{"index":66,"min":{"x":-64.0,"y":-8.0,"z":-72.0},"max":{"x":64.0,"y":8.0,"z":72.0},"origin":{"x":0.0,"y":0.0,"z":0.0},"headNode":{"plane":{"norm":{"x":1.0,"y":0.0,"z":0.0},"dist":-64.0},"children":[{"plane":{"norm":{"x":1.0,"y":0.0,"z":0.0},"dist":64.0},"children":[{"index":4939,"flags":1,"hasFaces":false,"min":{"x":64.0,"y":-16.0,"z":-80.0},"max":{"x":72.0,"y":16.0,"z":80.0}},{"plane":{"norm":{"x":0.0,"y":1.0,"z":0.0},"dist":-8.0},"children":[{"plane":{"norm":{"x":0.0,"y":1.0,"z":0.0},"dist":8.0},"children":[{"index":4940,"flags":1,"hasFaces":false,"min":{"x":-64.0,"y":8.0,"z":-80.0},"max":{"x":64.0,"y":16.0,"z":80.0}},{"plane":{"norm":{"x":0.0,"y":0.0,"z":1.0},"dist":-72.0},"children":[{"plane":{"norm":{"x":0.0,"y":0.0,"z":1.0},"dist":72.0},"children":[{"index":4941,"flags":1,"hasFaces":false,"min":{"x":-64.0,"y":-8.0,"z":72.0},"max":{"x":64.0,"y":8.0,"z":80.0}},{"index":4942,"flags":1,"hasFaces":false,"min":{"x":-64.0,"y":-8.0,"z":-72.0},"max":{"x":64.0,"y":8.0,"z":72.0}}],"min":{"x":-64.0,"y":-8.0,"z":-72.0},"max":{"x":64.0,"y":8.0,"z":80.0}},{"index":4943,"flags":1,"hasFaces":false,"min":{"x":-64.0,"y":-8.0,"z":-80.0},"max":{"x":64.0,"y":8.0,"z":-72.0}}],"min":{"x":-64.0,"y":-8.0,"z":-80.0},"max":{"x":64.0,"y":8.0,"z":80.0}}],"min":{"x":-64.0,"y":-8.0,"z":-80.0},"max":{"x":64.0,"y":16.0,"z":80.0}},{"index":4944,"flags":1,"hasFaces":false,"min":{"x":-64.0,"y":-16.0,"z":-80.0},"max":{"x":64.0,"y":-8.0,"z":80.0}}],"min":{"x":-64.0,"y":-16.0,"z":-80.0},"max":{"x":64.0,"y":16.0,"z":80.0}}],"min":{"x":-64.0,"y":-16.0,"z":-80.0},"max":{"x":72.0,"y":16.0,"z":80.0}},{"index":4945,"flags":1,"hasFaces":false,"min":{"x":-72.0,"y":-16.0,"z":-80.0},"max":{"x":-64.0,"y":16.0,"z":80.0}}],"min":{"x":-72.0,"y":-16.0,"z":-80.0},"max":{"x":72.0,"y":16.0,"z":80.0}}}