{"index":106,"min":{"x":-0.209991455,"y":-158.51001,"z":-93.0},"max":{"x":0.199996948,"y":1.48999023,"z":42.0},"origin":{"x":0.0,"y":0.0,"z":0.0},"headNode":{"plane":{"norm":{"x":0.0,"y":0.0,"z":1.0},"dist":39.0},"children":[{"plane":{"norm":{"x":1.0,"y":0.0,"z":0.0},"dist":-0.209991455},"children":[{"plane":{"norm":{"x":1.0,"y":0.0,"z":0.0},"dist":0.199996948},"children":[{"index":4733,"flags":1,"hasFaces":false,"min":{"x":0.0,"y":-166.0,"z":39.0},"max":{"x":8.0,"y":9.0,"z":50.0}},{"plane":{"norm":{"x":0.0,"y":1.0,"z":0.0},"dist":-158.51001},"children":[{"plane":{"norm":{"x":0.0,"y":1.0,"z":0.0},"dist":1.48999023},"children":[{"index":4734,"flags":1,"hasFaces":true,"min":{"x":0.0,"y":1.0,"z":39.0},"max":{"x":0.0,"y":9.0,"z":50.0}},{"plane":{"norm":{"x":0.0,"y":0.0,"z":1.0},"dist":42.0},"children":[{"index":4735,"flags":1,"hasFaces":true,"min":{"x":0.0,"y":-158.0,"z":42.0},"max":{"x":0.0,"y":1.0,"z":50.0}},{"index":4736,"flags":0,"hasFaces":false,"min":{"x":0.0,"y":-158.0,"z":39.0},"max":{"x":0.0,"y":1.0,"z":42.0}}],"min":{"x":0.0,"y":-158.0,"z":39.0},"max":{"x":0.0,"y":1.0,"z":50.0}}],"min":{"x":0.0,"y":-158.0,"z":39.0},"max":{"x":0.0,"y":9.0,"z":50.0}},{"index":4737,"flags":1,"hasFaces":true,"min":{"x":0.0,"y":-166.0,"z":39.0},"max":{"x":0.0,"y":-158.0,"z":50.0}}],"min":{"x":0.0,"y":-166.0,"z":39.0},"max":{"x":0.0,"y":9.0,"z":50.0}}],"min":{"x":0.0,"y":-166.0,"z":39.0},"max":{"x":8.0,"y":9.0,"z":50.0}},{"index":4738,"flags":1,"hasFaces":true,"min":{"x":-8.0,"y":-166.0,"z":39.0},"max":{"x":0.0,"y":9.0,"z":50.0}}],"min":{"x":-8.0,"y":-166.0,"z":39.0},"max":{"x":8.0,"y":9.0,"z":50.0}},{"plane":{"norm":{"x":1.0,"y":0.0,"z":0.0},"dist":-0.209991455},"children":[{"plane":{"norm":{"x":1.0,"y":0.0,"z":0.0},"dist":0.199996948},"children":[{"index":4739,"flags":1,"hasFaces":false,"min":{"x":0.0,"y":-166.0,"z":-101.0},"max":{"x":8.0,"y":9.0,"z":39.0}},{"plane":{"norm":{"x":0.0,"y":0.0,"z":1.0},"dist":-93.0},"children":[{"plane":{"norm":{"x":0.0,"y":1.0,"z":0.0},"dist":-1.51000977},"children":[{"plane":{"norm":{"x":0.0,"y":1.0,"z":0.0},"dist":1.48999023},"children":[{"index":4740,"flags":1,"hasFaces":true,"min":{"x":0.0,"y":1.0,"z":-93.0},"max":{"x":0.0,"y":9.0,"z":39.0}},{"index":4741,"flags":0,"hasFaces":false,"min":{"x":0.0,"y":-1.0,"z":-93.0},"max":{"x":0.0,"y":1.0,"z":39.0}}],"min":{"x":0.0,"y":-1.0,"z":-93.0},"max":{"x":0.0,"y":9.0,"z":39.0}},{"plane":{"norm":{"x":0.0,"y":1.0,"z":0.0},"dist":-158.51001},"children":[{"plane":{"norm":{"x":0.0,"y":1.0,"z":0.0},"dist":-155.51001},"children":[{"index":4742,"flags":1,"hasFaces":true,"min":{"x":0.0,"y":-155.0,"z":-93.0},"max":{"x":0.0,"y":-1.0,"z":39.0}},{"index":4743,"flags":0,"hasFaces":false,"min":{"x":0.0,"y":-158.0,"z":-93.0},"max":{"x":0.0,"y":-155.0,"z":39.0}}],"min":{"x":0.0,"y":-158.0,"z":-93.0},"max":{"x":0.0,"y":-1.0,"z":39.0}},{"index":4744,"flags":1,"hasFaces":true,"min":{"x":0.0,"y":-166.0,"z":-93.0},"max":{"x":0.0,"y":-158.0,"z":39.0}}],"min":{"x":0.0,"y":-166.0,"z":-93.0},"max":{"x":0.0,"y":-1.0,"z":39.0}}],"min":{"x":0.0,"y":-166.0,"z":-93.0},"max":{"x":0.0,"y":9.0,"z":39.0}},{"index":4745,"flags":1,"hasFaces":false,"min":{"x":0.0,"y":-166.0,"z":-101.0},"max":{"x":0.0,"y":9.0,"z":-93.0}}],"min":{"x":0.0,"y":-166.0,"z":-101.0},"max":{"x":0.0,"y":9.0,"z":39.0}}],"min":{"x":0.0,"y":-166.0,"z":-101.0},"max":{"x":8.0,"y":9.0,"z":39.0}},{"index":4746,"flags":1,"hasFaces":true,"min":{"x":-8.0,"y":-166.0,"z":-101.0},"max":{"x":0.0,"y":9.0,"z":39.0}}],"min":{"x":-8.0,"y":-166.0,"z":-101.0},"max":{"x":8.0,"y":9.0,"z":39.0}}],"min":{"x":-8.0,"y":-166.0,"z":-101.0},"max":{"x":8.0,"y":9.0,"z":50.0}}}