{"index":54,"min":{"x":-66.5,"y":-12.0039063,"z":-31.5},"max":{"x":63.5,"y":12.0039063,"z":31.5},"origin":{"x":0.0,"y":0.0,"z":0.0},"headNode":{"plane":{"norm":{"x":1.0,"y":0.0,"z":0.0},"dist":-66.5},"children":[{"plane":{"norm":{"x":1.0,"y":0.0,"z":0.0},"dist":63.5},"children":[{"index":4190,"flags":1,"hasFaces":true,"min":{"x":63.0,"y":-20.0,"z":-39.0},"max":{"x":71.0,"y":20.0,"z":39.0}},{"plane":{"norm":{"x":0.0,"y":0.0,"z":1.0},"dist":-31.5},"children":[{"plane":{"norm":{"x":0.0,"y":0.0,"z":1.0},"dist":31.5},"children":[{"index":4191,"flags":1,"hasFaces":true,"min":{"x":-66.0,"y":-20.0,"z":31.0},"max":{"x":63.0,"y":20.0,"z":39.0}},{"plane":{"norm":{"x":-0.07534969,"y":-0.979545951,"z":-0.186580181},"dist":1.09259033},"children":[{"index":4192,"flags":1,"hasFaces":false,"min":{"x":-66.0,"y":-20.0,"z":-31.0},"max":{"x":63.0,"y":9.0,"z":31.0}},{"plane":{"norm":{"x":0.07534969,"y":0.979545951,"z":0.186580181},"dist":0.8665161},"children":[{"index":4193,"flags":1,"hasFaces":true,"min":{"x":-66.0,"y":-10.0,"z":-31.0},"max":{"x":63.0,"y":20.0,"z":31.0}},{"index":4194,"flags":0,"hasFaces":false,"min":{"x":-66.0,"y":-12.0,"z":-31.0},"max":{"x":63.0,"y":11.0,"z":31.0}}],"min":{"x":-66.0,"y":-12.0,"z":-31.0},"max":{"x":63.0,"y":20.0,"z":31.0}}],"min":{"x":-66.0,"y":-20.0,"z":-31.0},"max":{"x":63.0,"y":20.0,"z":31.0}}],"min":{"x":-66.0,"y":-20.0,"z":-31.0},"max":{"x":63.0,"y":20.0,"z":39.0}},{"index":4195,"flags":1,"hasFaces":false,"min":{"x":-66.0,"y":-20.0,"z":-39.0},"max":{"x":63.0,"y":20.0,"z":-31.0}}],"min":{"x":-66.0,"y":-20.0,"z":-39.0},"max":{"x":63.0,"y":20.0,"z":39.0}}],"min":{"x":-66.0,"y":-20.0,"z":-39.0},"max":{"x":71.0,"y":20.0,"z":39.0}},{"index":4196,"flags":1,"hasFaces":false,"min":{"x":-74.0,"y":-20.0,"z":-39.0},"max":{"x":-66.0,"y":20.0,"z":39.0}}],"min":{"x":-74.0,"y":-20.0,"z":-39.0},"max":{"x":71.0,"y":20.0,"z":39.0}}}