{"index":47,"min":{"x":-56.0,"y":-80.0,"z":-192.0},"max":{"x":56.0019569,"y":80.0,"z":192.0},"origin":{"x":0.0,"y":0.0,"z":0.0},"headNode":{"plane":{"norm":{"x":0.0,"y":1.0,"z":0.0},"dist":-80.0},"children":[{"plane":{"norm":{"x":0.0,"y":1.0,"z":0.0},"dist":80.0},"children":[{"index":3292,"flags":3,"hasFaces":false,"min":{"x":-64.0,"y":80.0,"z":-200.0},"max":{"x":64.0,"y":88.0,"z":200.0}},{"plane":{"norm":{"x":0.0,"y":0.0,"z":1.0},"dist":-192.0},"children":[{"plane":{"norm":{"x":0.0,"y":0.0,"z":1.0},"dist":192.0},"children":[{"index":3293,"flags":3,"hasFaces":false,"min":{"x":-64.0,"y":-80.0,"z":192.0},"max":{"x":64.0,"y":80.0,"z":200.0}},{"plane":{"norm":{"x":-0.8574929,"y":0.5144958,"z":0.0},"dist":6.85998535},"children":[{"index":3294,"flags":3,"hasFaces":false,"min":{"x":-64.0,"y":-80.0,"z":-192.0},"max":{"x":40.0,"y":80.0,"z":192.0}},{"plane":{"norm":{"x":0.8574929,"y":-0.5144958,"z":0.0},"dist":6.85998535},"children":[{"index":3295,"flags":3,"hasFaces":false,"min":{"x":-40.0,"y":-80.0,"z":-192.0},"max":{"x":64.0,"y":80.0,"z":192.0}},{"index":3296,"flags":3,"hasFaces":false,"min":{"x":-56.0,"y":-80.0,"z":-192.0},"max":{"x":56.0,"y":80.0,"z":192.0}}],"min":{"x":-56.0,"y":-80.0,"z":-192.0},"max":{"x":64.0,"y":80.0,"z":192.0}}],"min":{"x":-64.0,"y":-80.0,"z":-192.0},"max":{"x":64.0,"y":80.0,"z":192.0}}],"min":{"x":-64.0,"y":-80.0,"z":-192.0},"max":{"x":64.0,"y":80.0,"z":200.0}},{"index":3297,"flags":3,"hasFaces":false,"min":{"x":-64.0,"y":-80.0,"z":-200.0},"max":{"x":64.0,"y":80.0,"z":-192.0}}],"min":{"x":-64.0,"y":-80.0,"z":-200.0},"max":{"x":64.0,"y":80.0,"z":200.0}}],"min":{"x":-64.0,"y":-80.0,"z":-200.0},"max":{"x":64.0,"y":88.0,"z":200.0}},{"index":3298,"flags":3,"hasFaces":false,"min":{"x":-64.0,"y":-88.0,"z":-200.0},"max":{"x":64.0,"y":-80.0,"z":200.0}}],"min":{"x":-64.0,"y":-88.0,"z":-200.0},"max":{"x":64.0,"y":88.0,"z":200.0}}}